{"errors":[],"warnings":[],"namedChunkGroups":{"app":{"chunks":[4,1,0],"assets":["webpack-runtime-77c3010e0024221e24f9.js","webpack-runtime-77c3010e0024221e24f9.js.map","commons-98d57ae15d0279ec73d9.js","commons-98d57ae15d0279ec73d9.js.map","app-9e6216d0da6da32a10c2.js","app-9e6216d0da6da32a10c2.js.map"],"children":{},"childAssets":{}},"component---src-pages-index-tsx":{"chunks":[3,2],"assets":["styles.6da6c935016c28713001.css","styles-be6f84f2f31d48e2088e.js","styles-be6f84f2f31d48e2088e.js.map","component---src-pages-index-tsx-7256e10ec71e99c794b6.js","component---src-pages-index-tsx-7256e10ec71e99c794b6.js.map"],"children":{},"childAssets":{}}},"assetsByChunkName":{"app":["webpack-runtime-77c3010e0024221e24f9.js","commons-98d57ae15d0279ec73d9.js","app-9e6216d0da6da32a10c2.js"],"component---src-pages-index-tsx":["styles.6da6c935016c28713001.css","styles-be6f84f2f31d48e2088e.js","component---src-pages-index-tsx-7256e10ec71e99c794b6.js"]}}