{"errors":[],"warnings":[],"namedChunkGroups":{"app":{"chunks":[4,1,0],"assets":["webpack-runtime-f58190b3d989b0a40e0d.js","webpack-runtime-f58190b3d989b0a40e0d.js.map","commons-e721db8c56d72ec221c3.js","commons-e721db8c56d72ec221c3.js.map","app-77d6e0eba3012601f85a.js","app-77d6e0eba3012601f85a.js.map"],"children":{},"childAssets":{}},"component---src-pages-index-tsx":{"chunks":[3,2],"assets":["styles.3c544ab95351da90915b.css","styles-b1feb9aba8257b4402e4.js","styles-b1feb9aba8257b4402e4.js.map","component---src-pages-index-tsx-e705f881cd7050e7f503.js","component---src-pages-index-tsx-e705f881cd7050e7f503.js.map"],"children":{},"childAssets":{}}},"assetsByChunkName":{"app":["webpack-runtime-f58190b3d989b0a40e0d.js","commons-e721db8c56d72ec221c3.js","app-77d6e0eba3012601f85a.js"],"component---src-pages-index-tsx":["styles.3c544ab95351da90915b.css","styles-b1feb9aba8257b4402e4.js","component---src-pages-index-tsx-e705f881cd7050e7f503.js"]}}