{"errors":[],"warnings":[],"namedChunkGroups":{"app":{"chunks":[4,1,0],"assets":["webpack-runtime-71409bca15109f27c8d5.js","webpack-runtime-71409bca15109f27c8d5.js.map","commons-a7a498086666f1bd1e9f.js","commons-a7a498086666f1bd1e9f.js.map","app-9222f2f17288661baced.js","app-9222f2f17288661baced.js.map"],"children":{},"childAssets":{}},"component---src-pages-index-tsx":{"chunks":[3,2],"assets":["styles.3c544ab95351da90915b.css","styles-0a9fa9e343dad9249fa5.js","styles-0a9fa9e343dad9249fa5.js.map","component---src-pages-index-tsx-a95418004732b3f2ed66.js","component---src-pages-index-tsx-a95418004732b3f2ed66.js.map"],"children":{},"childAssets":{}}},"assetsByChunkName":{"app":["webpack-runtime-71409bca15109f27c8d5.js","commons-a7a498086666f1bd1e9f.js","app-9222f2f17288661baced.js"],"component---src-pages-index-tsx":["styles.3c544ab95351da90915b.css","styles-0a9fa9e343dad9249fa5.js","component---src-pages-index-tsx-a95418004732b3f2ed66.js"]}}